Metadata-Version: 2.4
Name: flexible-fl
Version: 0.7.0
Home-page: https://github.com/FLEXible-FL/FLEX-framework
Author: Jimenez-Lopez Daniel, Argente-Garrido Alberto
Author-email: xehartnort@gmail.com, albertoargentedcgarrido@gmail.com
Keywords: FL federated-learning flexible
Classifier: Development Status :: 4 - Beta
Classifier: Intended Audience :: Science/Research
Classifier: Topic :: Software Development :: Build Tools
Classifier: License :: OSI Approved :: GNU Affero General Public License v3 or later (AGPLv3+)
Classifier: Programming Language :: Python :: 3
Classifier: Programming Language :: Python :: 3.9
Classifier: Programming Language :: Python :: 3.10
Classifier: Programming Language :: Python :: 3.11
Classifier: Programming Language :: Python :: 3.12
Classifier: Programming Language :: Python :: 3 :: Only
Requires-Python: >=3.9
Requires-Dist: numpy
Requires-Dist: multiprocess
Requires-Dist: scikit-learn
Requires-Dist: cardinality
Requires-Dist: sultan
Requires-Dist: tqdm
Requires-Dist: scipy
Requires-Dist: gdown
Requires-Dist: tensorly
Provides-Extra: tensorflow
Requires-Dist: tensorflow; extra == "tensorflow"
Requires-Dist: tensorflow_datasets; extra == "tensorflow"
Requires-Dist: tensorflow_hub; extra == "tensorflow"
Provides-Extra: pytorch
Requires-Dist: torch; extra == "pytorch"
Requires-Dist: torchvision; extra == "pytorch"
Requires-Dist: torchtext; extra == "pytorch"
Requires-Dist: torchdata; extra == "pytorch"
Requires-Dist: portalocker; extra == "pytorch"
Provides-Extra: hugginface
Requires-Dist: datasets; extra == "hugginface"
Provides-Extra: distributed
Requires-Dist: grpcio; extra == "distributed"
Requires-Dist: protobuf; extra == "distributed"
Provides-Extra: develop
Requires-Dist: pytest; extra == "develop"
Requires-Dist: pytest-asyncio; extra == "develop"
Requires-Dist: pytest-cov; extra == "develop"
Requires-Dist: pytest-xdist; extra == "develop"
Requires-Dist: coverage; extra == "develop"
Requires-Dist: jinja2; extra == "develop"
Requires-Dist: tensorflow; extra == "develop"
Requires-Dist: tensorflow_datasets; extra == "develop"
Requires-Dist: tensorflow_hub; extra == "develop"
Requires-Dist: torch; extra == "develop"
Requires-Dist: torchvision; extra == "develop"
Requires-Dist: torchtext; extra == "develop"
Requires-Dist: torchdata; extra == "develop"
Requires-Dist: portalocker; extra == "develop"
Requires-Dist: datasets; extra == "develop"
Requires-Dist: grpcio; extra == "develop"
Requires-Dist: protobuf; extra == "develop"
Requires-Dist: grpcio-tools; extra == "develop"
Dynamic: author
Dynamic: author-email
Dynamic: classifier
Dynamic: description
Dynamic: description-content-type
Dynamic: home-page
Dynamic: keywords
Dynamic: provides-extra
Dynamic: requires-dist
Dynamic: requires-python
